<list
  id="contacts"
  trigger="refresh"
  action="replace"
  href="?page=1&amp;template=list"
  target="contacts"
  keyboard-dismiss-mode="on-drag"
  xmlns="https://hyperview.org/hyperview"
>
  
  <item key="search" id="top" sticky="true" style="relative mx-24">
    <text-field
      placeholder="Search a contact…"
      placeholderTextColor="#8D9494"
      name="search"
      style="input"
      debounce="200"
      value=""
    >
      
      
      
      
      <behavior
        trigger="change"
        action="hide"
        target="load-more"
      />
      <behavior
        trigger="change"
        action="scroll"
        target="top"
        xmlns:scroll="https://hyperview.org/hyperview-scroll"
      />
      <behavior
        trigger="change"
        action="replace"
        target="contacts"
        href="?template=list"
        show-during-load="loading-indicator"
      />
    </text-field>
    <view id="loading-indicator" style="absolute r-0 py-8" hide="true">
      <spinner />
    </view>
  </item>
  <items xmlns="https://hyperview.org/hyperview">
  
    <item key="72d4dba0-3d9c-4f11-874c-9f02a130e9ca" style="mx-24 py-8 border-bottom">
      <text>Aaron Brown</text>
      <text>Anika19@hotmail.com</text>
      <text>(832) 555-2266</text>
    </item>
  
    <item key="76871e30-3e22-422d-9c71-e65a5cf57fbf" style="mx-24 py-8 border-bottom">
      <text>Aaron Christiansen V</text>
      <text>Llewellyn61@gmail.com</text>
      <text>(120) 555-0035</text>
    </item>
  
    <item key="d9ea27ab-a2e4-4ec8-abd1-2de0de476bec" style="mx-24 py-8 border-bottom">
      <text>Aaron Grant</text>
      <text>Maryam_Bednar97@yahoo.com</text>
      <text>(377) 555-8818</text>
    </item>
  
    <item key="3e172f24-18c9-4909-8f79-b47be56dbe83" style="mx-24 py-8 border-bottom">
      <text>Aaron Harvey</text>
      <text>Timothy43@hotmail.com</text>
      <text>(290) 555-7723</text>
    </item>
  
    <item key="c66fdecb-9f33-4e68-a4d5-78a381826bf3" style="mx-24 py-8 border-bottom">
      <text>Aaron Hills</text>
      <text>Reinhold_Kuhic@hotmail.com</text>
      <text>(921) 555-3906</text>
    </item>
  
    <item key="0d9374ba-ebf2-430f-9592-487651858168" style="mx-24 py-8 border-bottom">
      <text>Aaron Hilpert</text>
      <text>Brenden.Rodriguez36@hotmail.com</text>
      <text>(739) 555-8380</text>
    </item>
  
    <item key="5df6f804-6d5c-4a9f-8d60-514b9a58cb43" style="mx-24 py-8 border-bottom">
      <text>Aaron Macejkovic</text>
      <text>June_DAmore84@gmail.com</text>
      <text>(019) 555-4802</text>
    </item>
  
    <item key="035ed24a-5e9f-4dec-ab3e-ab5c3fd8280c" style="mx-24 py-8 border-bottom">
      <text>Aaron Marvin</text>
      <text>Felicita65@gmail.com</text>
      <text>(917) 555-9828</text>
    </item>
  
    <item key="fadaf897-f500-4c03-83f7-3db70286f3d7" style="mx-24 py-8 border-bottom">
      <text>Aaron Okuneva</text>
      <text>Queen.Hermiston@yahoo.com</text>
      <text>(582) 555-6849</text>
    </item>
  
    <item key="a4396212-fef5-424f-a952-fd4d9ecf7859" style="mx-24 py-8 border-bottom">
      <text>Aaron Rohan</text>
      <text>Morton1@gmail.com</text>
      <text>(442) 555-7256</text>
    </item>
  
    <item key="fd63c97f-7588-41fa-9dfa-b7f0a85c2cc8" style="mx-24 py-8 border-bottom">
      <text>Aaron Sipes</text>
      <text>Keith.Brakus63@yahoo.com</text>
      <text>(635) 555-0317</text>
    </item>
  
    <item key="b0e194ca-ceb3-4e95-8411-bcc0d523c37f" style="mx-24 py-8 border-bottom">
      <text>Aaron Terry</text>
      <text>Selmer90@yahoo.com</text>
      <text>(794) 555-8830</text>
    </item>
  
    <item key="0c63cd2c-4e5d-43b6-8e3f-324dbbd48710" style="mx-24 py-8 border-bottom">
      <text>Aaron Thiel</text>
      <text>Zackary.Bode@hotmail.com</text>
      <text>(289) 555-9305</text>
    </item>
  
    <item key="473620c4-b453-4409-a00f-fe01ad715623" style="mx-24 py-8 border-bottom">
      <text>Aaron Walter</text>
      <text>Merlin_OKon59@hotmail.com</text>
      <text>(467) 555-4511</text>
    </item>
  
    <item key="4b616e33-78e6-4220-b3d4-12155cc0d7b2" style="mx-24 py-8 border-bottom">
      <text>Aaron Ward</text>
      <text>Karson_Moore29@yahoo.com</text>
      <text>(744) 555-9764</text>
    </item>
  
    <item key="f85ce860-5a36-4e67-8552-2fdca26a03a8" style="mx-24 py-8 border-bottom">
      <text>Aaron Weber</text>
      <text>Ole42@hotmail.com</text>
      <text>(953) 555-9973</text>
    </item>
  
    <item key="f18d5ac2-cbb4-4bc8-9172-fa521ed443cc" style="mx-24 py-8 border-bottom">
      <text>Abel Beahan</text>
      <text>Ava55@yahoo.com</text>
      <text>(755) 555-9055</text>
    </item>
  
    <item key="af02d132-b219-4656-8b3d-89f606a46882" style="mx-24 py-8 border-bottom">
      <text>Abel Collier</text>
      <text>Stella_Olson@gmail.com</text>
      <text>(657) 555-9532</text>
    </item>
  
    <item key="02df31ca-be6e-4aea-b4a6-88872ecb667a" style="mx-24 py-8 border-bottom">
      <text>Abel Davis</text>
      <text>Sophie_Krajcik98@yahoo.com</text>
      <text>(073) 555-7818</text>
    </item>
  
    <item key="044045a5-a69b-44bc-aa80-e496cb837e36" style="mx-24 py-8 border-bottom">
      <text>Abel Greenholt</text>
      <text>Hayley_Howell@hotmail.com</text>
      <text>(661) 555-9200</text>
    </item>
  
  
    <item
      key="load-more"
      id="load-more"
      trigger="visible"
      action="replace"
      href="?page=2"
    >
      <spinner />
    </item>
  
</items>

</list>
